<?xml version="1.0" encoding="UTF-8"?>

<auseiMcmc version="4.0beta">
	<path>
		<population>popfile.csv</population>
		<epidemic>epifile.csv</epidemic>
		<outputPrefix>outputPrefix</outputPrefix>
	</path>

	<options>
		<obstime>365.0</obstime>
		<omega>1</omega>
		<nu>0.16667</nu>
	</options>

	<parameters>
		<epsilon0>
			<prior>
				<distribution>gamma</distribution>
				<alpha>1</alpha>
				<beta>1</beta>
			</prior>
			<init>3e-4</init>
		</epsilon0>
		<epsilon10>
			<prior>
				<distribution>gamma</distribution>
				<alpha>1</alpha>
				<beta>1</beta>
			</prior>
			<init>0.01</init>
		</epsilon10>
		<epsilon44>
			<prior>
				<distribution>gamma</distribution>
				<alpha>1</alpha>
				<beta>1</beta>
			</prior>
			<init>0.0001</init>
		</epsilon44>
		<mu>
			<prior>
				<distribution>gamma</distribution>
				<alpha>1</alpha>
				<beta>1</beta>
			</prior>
			<init>0.0019</init>
		</mu>
		<xi>
			<prior>
				<distribution>gaussian</distribution>
				<mean>0.0</mean>
				<var>0.1</var>
			</prior>
			<init>0.0</init>
		</xi>
		<zeta>
			<prior>
				<distribution>gaussian</distribution>
				<mean>0.0</mean>
				<var>0.1</var>
			</prior>
			<init>0.0</init>
		</zeta>
		<delta>
			<prior>
				<distribution>gamma</distribution>
				<alpha>1</alpha>
				<beta>1</beta>
			</prior>
			<init>0.1</init>
		</delta>
		<theta>
			<prior>
				<distribution>beta</distribution>
				<alpha>2</alpha>
				<beta>2</beta>
			</prior>
			<init>0.13</init>
		</theta>
		<b>
			<prior>
				<distribution>gamma</distribution>
				<alpha>1</alpha>
				<beta>1</beta>
			</prior>
			<init>0.4</init>
		</b>
	</parameters>

	<mcmc>
		<tune>
			<mu>0.1</mu>
			<delta>0.1</delta>
			<theta>0.6</theta>
			<b>0.1</b>
		</tune>
		<iterations>10000</iterations>
		<seed>0</seed>
	</mcmc>

</auseiMcmc>

